{"blt6e971255399a26bb":{"uid":"blt6e971255399a26bb","content_type":"image/jpeg","file_size":"41226","tags":[],"filename":"Maya_Angelou_Headshot.jpg","url":"https://images.contentstack.io/v3/assets/<api_key>/<asset_uid>/<entity_uid>/<asset_name>","ACL":{"roles":[],"others":{"read":false,"create":false,"update":false,"delete":false,"sub_acl":{"read":false,"create":false,"update":false,"delete":false,"publish":false}}},"is_dir":false,"parent_uid":"blt0aebf788c355c655","_version":1,"title":"Maya Angelou","description":"","publish_details":[{"environment":"blt6f0478243197ef17","locale":"en-us","time":"2022-05-20T06:47:10.868Z","version":1},{"environment":"blt92be63b2b247a1c5","locale":"en-us","time":"2022-05-20T06:47:10.873Z","version":1},{"environment":"bltef79978048f9cf2a","locale":"en-us","time":"2022-05-20T06:47:10.880Z","version":1}]},"blt9a5a0666e3fde0b2":{"uid":"blt9a5a0666e3fde0b2","content_type":"image/svg+xml","file_size":"76596","tags":[],"filename":"our-story.svg","url":"https://images.contentstack.io/v3/assets/<api_key>/<asset_uid>/<entity_uid>/<asset_name>","ACL":{"roles":[],"others":{"read":false,"create":false,"update":false,"delete":false,"sub_acl":{"read":false,"create":false,"update":false,"delete":false,"publish":false}}},"is_dir":false,"parent_uid":"blt43987a02bf0d77e9","_version":1,"title":"our-story.svg","publish_details":[{"environment":"blt6f0478243197ef17","locale":"en-us","time":"2022-05-20T06:47:10.956Z","version":1},{"environment":"blt92be63b2b247a1c5","locale":"en-us","time":"2022-05-20T06:47:10.961Z","version":1},{"environment":"bltef79978048f9cf2a","locale":"en-us","time":"2022-05-20T06:47:10.964Z","version":1}]},"bltb7844b792d3b673d":{"uid":"bltb7844b792d3b673d","content_type":"image/svg+xml","file_size":"47003","tags":[],"filename":"modern-cloud-ecosystem.svg","url":"https://images.contentstack.io/v3/assets/<api_key>/<asset_uid>/<entity_uid>/<asset_name>","ACL":{"roles":[],"others":{"read":false,"create":false,"update":false,"delete":false,"sub_acl":{"read":false,"create":false,"update":false,"delete":false,"publish":false}}},"is_dir":false,"parent_uid":"blt8ea21a022f87ea56","_version":1,"title":"Modern Cloud Ecosystem","description":"","publish_details":[{"environment":"blt6f0478243197ef17","locale":"en-us","time":"2022-05-20T06:47:09.329Z","version":1},{"environment":"blt92be63b2b247a1c5","locale":"en-us","time":"2022-05-20T06:47:09.332Z","version":1},{"environment":"bltef79978048f9cf2a","locale":"en-us","time":"2022-05-20T06:47:09.337Z","version":1}]},"blt0b430723c823dba7":{"uid":"blt0b430723c823dba7","content_type":"image/svg+xml","file_size":"48517","tags":[],"filename":"pierre-cox.svg","url":"https://images.contentstack.io/v3/assets/<api_key>/<asset_uid>/<entity_uid>/<asset_name>","ACL":{"roles":[],"others":{"read":false,"create":false,"update":false,"delete":false,"sub_acl":{"read":false,"create":false,"update":false,"delete":false,"publish":false}}},"is_dir":false,"parent_uid":"blt43987a02bf0d77e9","_version":1,"title":"pierre-cox.svg","publish_details":[{"environment":"blt6f0478243197ef17","locale":"en-us","time":"2022-05-20T06:47:12.203Z","version":1},{"environment":"blt92be63b2b247a1c5","locale":"en-us","time":"2022-05-20T06:47:12.207Z","version":1},{"environment":"bltef79978048f9cf2a","locale":"en-us","time":"2022-05-20T06:47:12.210Z","version":1}]},"blt5beb5c63284ebc32":{"uid":"blt5beb5c63284ebc32","content_type":"image/svg+xml","file_size":"154333","tags":[],"filename":"cierra-vega.svg","url":"https://images.contentstack.io/v3/assets/<api_key>/<asset_uid>/<entity_uid>/<asset_name>","ACL":{"roles":[],"others":{"read":false,"create":false,"update":false,"delete":false,"sub_acl":{"read":false,"create":false,"update":false,"delete":false,"publish":false}}},"is_dir":false,"parent_uid":"blt43987a02bf0d77e9","_version":1,"title":"Cierra Vega","description":"","publish_details":[{"environment":"blt6f0478243197ef17","locale":"en-us","time":"2022-05-20T06:47:12.793Z","version":1},{"environment":"blt92be63b2b247a1c5","locale":"en-us","time":"2022-05-20T06:47:12.801Z","version":1},{"environment":"bltef79978048f9cf2a","locale":"en-us","time":"2022-05-20T06:47:12.807Z","version":1}]},"blte7a689e0223a94e5":{"uid":"blte7a689e0223a94e5","content_type":"image/svg+xml","file_size":"1053","tags":[],"filename":"bucket3.svg","url":"https://images.contentstack.io/v3/assets/<api_key>/<asset_uid>/<entity_uid>/<asset_name>","ACL":{"roles":[],"others":{"read":false,"create":false,"update":false,"delete":false,"sub_acl":{"read":false,"create":false,"update":false,"delete":false,"publish":false}}},"is_dir":false,"parent_uid":"bltc227ac394f06235b","_version":1,"title":"bucket3.svg","publish_details":[{"environment":"blt6f0478243197ef17","locale":"en-us","time":"2022-05-20T06:46:58.553Z","version":1},{"environment":"blt92be63b2b247a1c5","locale":"en-us","time":"2022-05-20T06:46:58.561Z","version":1},{"environment":"bltef79978048f9cf2a","locale":"en-us","time":"2022-05-20T06:46:58.567Z","version":1}]},"blt76e0e075602e5b0e":{"uid":"blt76e0e075602e5b0e","content_type":"image/png","file_size":"3938","tags":[],"filename":"cslogo.png","url":"https://images.contentstack.io/v3/assets/<api_key>/<asset_uid>/<entity_uid>/<asset_name>","ACL":{"roles":[],"others":{"read":false,"create":false,"update":false,"delete":false,"sub_acl":{"read":false,"create":false,"update":false,"delete":false,"publish":false}}},"is_dir":false,"parent_uid":"blt6b0daed53c373b40","_version":1,"title":"cslogo.png","publish_details":[{"environment":"blt6f0478243197ef17","locale":"en-us","time":"2022-05-20T06:46:58.570Z","version":1},{"environment":"blt92be63b2b247a1c5","locale":"en-us","time":"2022-05-20T06:46:58.578Z","version":1},{"environment":"bltef79978048f9cf2a","locale":"en-us","time":"2022-05-20T06:46:58.584Z","version":1}]},"blt00c50044f12cbcd3":{"uid":"blt00c50044f12cbcd3","content_type":"image/svg+xml","file_size":"54029","tags":[],"filename":"winning-digital-strategy.svg","url":"https://images.contentstack.io/v3/assets/<api_key>/<asset_uid>/<entity_uid>/<asset_name>","ACL":{"roles":[],"others":{"read":false,"create":false,"update":false,"delete":false,"sub_acl":{"read":false,"create":false,"update":false,"delete":false,"publish":false}}},"is_dir":false,"parent_uid":"blt2f83c9424aeedf29","_version":1,"title":"Winning Digital Strategy","description":"","publish_details":[{"environment":"blt6f0478243197ef17","locale":"en-us","time":"2022-05-20T06:47:00.213Z","version":1},{"environment":"blt92be63b2b247a1c5","locale":"en-us","time":"2022-05-20T06:47:00.219Z","version":1},{"environment":"bltef79978048f9cf2a","locale":"en-us","time":"2022-05-20T06:47:00.225Z","version":1}]},"blt5fbb2d40dac0962c":{"uid":"blt5fbb2d40dac0962c","content_type":"image/jpeg","file_size":"34781","tags":[],"filename":"Zora_Neale_Hurston_Headshot.jpg","url":"https://images.contentstack.io/v3/assets/<api_key>/<asset_uid>/<entity_uid>/<asset_name>","ACL":{"roles":[],"others":{"read":false,"create":false,"update":false,"delete":false,"sub_acl":{"read":false,"create":false,"update":false,"delete":false,"publish":false}}},"is_dir":false,"parent_uid":"blt0aebf788c355c655","_version":1,"title":"Zora Neale Hurston","description":"","publish_details":[{"environment":"blt6f0478243197ef17","locale":"en-us","time":"2022-05-20T06:47:01.652Z","version":1},{"environment":"blt92be63b2b247a1c5","locale":"en-us","time":"2022-05-20T06:47:01.656Z","version":1},{"environment":"bltef79978048f9cf2a","locale":"en-us","time":"2022-05-20T06:47:01.660Z","version":1}]},"blt348eb71d9fcb8489":{"uid":"blt348eb71d9fcb8489","content_type":"image/svg+xml","file_size":"125471","tags":[],"filename":"about-us.svg","url":"https://images.contentstack.io/v3/assets/<api_key>/<asset_uid>/<entity_uid>/<asset_name>","ACL":{"roles":[],"others":{"read":false,"create":false,"update":false,"delete":false,"sub_acl":{"read":false,"create":false,"update":false,"delete":false,"publish":false}}},"is_dir":false,"parent_uid":"blt43987a02bf0d77e9","_version":1,"title":"about-us.svg","publish_details":[{"environment":"blt6f0478243197ef17","locale":"en-us","time":"2022-05-20T06:47:00.229Z","version":1},{"environment":"blt92be63b2b247a1c5","locale":"en-us","time":"2022-05-20T06:47:00.236Z","version":1},{"environment":"bltef79978048f9cf2a","locale":"en-us","time":"2022-05-20T06:47:00.242Z","version":1}]},"blt5d03fb863b624dca":{"uid":"blt5d03fb863b624dca","content_type":"image/svg+xml","file_size":"55212","tags":[],"filename":"alden-cantrell.svg","url":"https://images.contentstack.io/v3/assets/<api_key>/<asset_uid>/<entity_uid>/<asset_name>","ACL":{"roles":[],"others":{"read":false,"create":false,"update":false,"delete":false,"sub_acl":{"read":false,"create":false,"update":false,"delete":false,"publish":false}}},"is_dir":false,"parent_uid":"blt43987a02bf0d77e9","_version":1,"title":"alden-cantrell.svg","publish_details":[{"environment":"blt6f0478243197ef17","locale":"en-us","time":"2022-05-20T06:47:03.193Z","version":1},{"environment":"blt92be63b2b247a1c5","locale":"en-us","time":"2022-05-20T06:47:03.197Z","version":1},{"environment":"bltef79978048f9cf2a","locale":"en-us","time":"2022-05-20T06:47:03.201Z","version":1}]},"blt3266b7b88da2f0c0":{"uid":"blt3266b7b88da2f0c0","content_type":"image/svg+xml","file_size":"11085","tags":[],"filename":"company-logo.svg","url":"https://images.contentstack.io/v3/assets/<api_key>/<asset_uid>/<entity_uid>/<asset_name>","ACL":{"roles":[],"others":{"read":false,"create":false,"update":false,"delete":false,"sub_acl":{"read":false,"create":false,"update":false,"delete":false,"publish":false}}},"is_dir":false,"parent_uid":"blt6b0daed53c373b40","_version":1,"title":"Company Logo","description":"","publish_details":[{"environment":"blt6f0478243197ef17","locale":"en-us","time":"2022-05-20T06:47:04.720Z","version":1},{"environment":"blt92be63b2b247a1c5","locale":"en-us","time":"2022-05-20T06:47:04.727Z","version":1},{"environment":"bltef79978048f9cf2a","locale":"en-us","time":"2022-05-20T06:47:04.733Z","version":1}]},"blt61b2f433c12f52f0":{"uid":"blt61b2f433c12f52f0","content_type":"image/png","file_size":"99632","tags":[],"filename":"Charlotte_Bronte_Headshot.png","url":"https://images.contentstack.io/v3/assets/<api_key>/<asset_uid>/<entity_uid>/<asset_name>","ACL":{"roles":[],"others":{"read":false,"create":false,"update":false,"delete":false,"sub_acl":{"read":false,"create":false,"update":false,"delete":false,"publish":false}}},"is_dir":false,"parent_uid":"blt0aebf788c355c655","_version":1,"title":"Charlotte Bronte","description":"","publish_details":[{"environment":"blt6f0478243197ef17","locale":"en-us","time":"2022-05-20T06:47:03.398Z","version":1},{"environment":"blt92be63b2b247a1c5","locale":"en-us","time":"2022-05-20T06:47:03.405Z","version":1},{"environment":"bltef79978048f9cf2a","locale":"en-us","time":"2022-05-20T06:47:03.412Z","version":1}]},"bltb0f79a770b8492b4":{"uid":"bltb0f79a770b8492b4","content_type":"image/svg+xml","file_size":"128164","tags":[],"filename":"thomas-crane.svg","url":"https://images.contentstack.io/v3/assets/<api_key>/<asset_uid>/<entity_uid>/<asset_name>","ACL":{"roles":[],"others":{"read":false,"create":false,"update":false,"delete":false,"sub_acl":{"read":false,"create":false,"update":false,"delete":false,"publish":false}}},"is_dir":false,"parent_uid":"blt43987a02bf0d77e9","_version":1,"title":"thomas-crane.svg","publish_details":[{"environment":"blt6f0478243197ef17","locale":"en-us","time":"2022-05-20T06:47:01.840Z","version":1},{"environment":"blt92be63b2b247a1c5","locale":"en-us","time":"2022-05-20T06:47:01.851Z","version":1},{"environment":"bltef79978048f9cf2a","locale":"en-us","time":"2022-05-20T06:47:01.858Z","version":1}]},"blt33688ca1f5bc8cd9":{"uid":"blt33688ca1f5bc8cd9","content_type":"image/jpeg","file_size":"31539","tags":[],"filename":"Charles_Dickens_Headshot.jpg","url":"https://images.contentstack.io/v3/assets/<api_key>/<asset_uid>/<entity_uid>/<asset_name>","ACL":{"roles":[],"others":{"read":false,"create":false,"update":false,"delete":false,"sub_acl":{"read":false,"create":false,"update":false,"delete":false,"publish":false}}},"is_dir":false,"parent_uid":"blt0aebf788c355c655","_version":1,"title":"Charles Dickens","description":"","publish_details":[{"environment":"blt6f0478243197ef17","locale":"en-us","time":"2022-05-20T06:47:06.045Z","version":1},{"environment":"blt92be63b2b247a1c5","locale":"en-us","time":"2022-05-20T06:47:06.049Z","version":1},{"environment":"bltef79978048f9cf2a","locale":"en-us","time":"2022-05-20T06:47:06.053Z","version":1}]},"blt3b98be2ddaf343e7":{"uid":"blt3b98be2ddaf343e7","content_type":"image/jpeg","file_size":"25872","tags":[],"filename":"W._E._B._Du_Bois_Headshot.jpg","url":"https://images.contentstack.io/v3/assets/<api_key>/<asset_uid>/<entity_uid>/<asset_name>","ACL":{"roles":[],"others":{"read":false,"create":false,"update":false,"delete":false,"sub_acl":{"read":false,"create":false,"update":false,"delete":false,"publish":false}}},"is_dir":false,"parent_uid":"blt0aebf788c355c655","_version":1,"title":"W.E. B. Du Bois","description":"","publish_details":[{"environment":"blt6f0478243197ef17","locale":"en-us","time":"2022-05-20T06:47:04.691Z","version":1},{"environment":"blt92be63b2b247a1c5","locale":"en-us","time":"2022-05-20T06:47:04.698Z","version":1},{"environment":"bltef79978048f9cf2a","locale":"en-us","time":"2022-05-20T06:47:04.703Z","version":1}]},"bltd0d9140def6be17e":{"uid":"bltd0d9140def6be17e","content_type":"image/jpeg","file_size":"21371","tags":[],"filename":"Virginia_Woolf_Headshot.jpg","url":"https://images.contentstack.io/v3/assets/<api_key>/<asset_uid>/<entity_uid>/<asset_name>","ACL":{"roles":[],"others":{"read":false,"create":false,"update":false,"delete":false,"sub_acl":{"read":false,"create":false,"update":false,"delete":false,"publish":false}}},"is_dir":false,"parent_uid":"blt0aebf788c355c655","_version":1,"title":"Virginia Woolf","description":"","publish_details":[{"environment":"blt6f0478243197ef17","locale":"en-us","time":"2022-05-20T06:47:07.900Z","version":1},{"environment":"blt92be63b2b247a1c5","locale":"en-us","time":"2022-05-20T06:47:07.903Z","version":1},{"environment":"bltef79978048f9cf2a","locale":"en-us","time":"2022-05-20T06:47:07.907Z","version":1}]},"blt80e38e99a2abce1b":{"uid":"blt80e38e99a2abce1b","content_type":"image/jpeg","file_size":"148713","tags":[],"filename":"Mark_Twain_Headshot.jpg","url":"https://images.contentstack.io/v3/assets/<api_key>/<asset_uid>/<entity_uid>/<asset_name>","ACL":{"roles":[],"others":{"read":false,"create":false,"update":false,"delete":false,"sub_acl":{"read":false,"create":false,"update":false,"delete":false,"publish":false}}},"is_dir":false,"parent_uid":"blt0aebf788c355c655","_version":1,"title":"Mark Twain","description":"","publish_details":[{"environment":"blt6f0478243197ef17","locale":"en-us","time":"2022-05-20T06:47:06.501Z","version":1},{"environment":"blt92be63b2b247a1c5","locale":"en-us","time":"2022-05-20T06:47:06.507Z","version":1},{"environment":"bltef79978048f9cf2a","locale":"en-us","time":"2022-05-20T06:47:06.512Z","version":1}]},"bltf260946fe036ffe5":{"uid":"bltf260946fe036ffe5","content_type":"image/svg+xml","file_size":"26826","tags":[],"filename":"business-with-al.svg","url":"https://images.contentstack.io/v3/assets/<api_key>/<asset_uid>/<entity_uid>/<asset_name>","ACL":{"roles":[],"others":{"read":false,"create":false,"update":false,"delete":false,"sub_acl":{"read":false,"create":false,"update":false,"delete":false,"publish":false}}},"is_dir":false,"parent_uid":"blt8ea21a022f87ea56","_version":1,"title":"Business With Al","description":"","publish_details":[{"environment":"blt6f0478243197ef17","locale":"en-us","time":"2022-05-20T06:47:07.882Z","version":1},{"environment":"blt92be63b2b247a1c5","locale":"en-us","time":"2022-05-20T06:47:07.888Z","version":1},{"environment":"bltef79978048f9cf2a","locale":"en-us","time":"2022-05-20T06:47:07.894Z","version":1}]},"blt6e9a989aba54225c":{"uid":"blt6e9a989aba54225c","content_type":"image/jpeg","file_size":"12668","tags":[],"filename":"Jane_Austen_Headshot.jpg","url":"https://images.contentstack.io/v3/assets/<api_key>/<asset_uid>/<entity_uid>/<asset_name>","ACL":{"roles":[],"others":{"read":false,"create":false,"update":false,"delete":false,"sub_acl":{"read":false,"create":false,"update":false,"delete":false,"publish":false}}},"is_dir":false,"parent_uid":"blt0aebf788c355c655","_version":1,"title":"Jane Austen","description":"","publish_details":[{"environment":"blt6f0478243197ef17","locale":"en-us","time":"2022-05-20T06:47:09.067Z","version":1},{"environment":"blt92be63b2b247a1c5","locale":"en-us","time":"2022-05-20T06:47:09.076Z","version":1},{"environment":"bltef79978048f9cf2a","locale":"en-us","time":"2022-05-20T06:47:09.083Z","version":1}]},"blt4c8e5022f2203dcb":{"uid":"blt4c8e5022f2203dcb","content_type":"image/svg+xml","file_size":"806","tags":[],"filename":"Instagram.svg","url":"https://images.contentstack.io/v3/assets/<api_key>/<asset_uid>/<entity_uid>/<asset_name>","ACL":{"roles":[],"others":{"read":false,"create":false,"update":false,"delete":false,"sub_acl":{"read":false,"create":false,"update":false,"delete":false,"publish":false}}},"is_dir":false,"parent_uid":"bltc227ac394f06235b","_version":1,"title":"Instagram.svg","description":"","publish_details":[{"environment":"blt6f0478243197ef17","locale":"en-us","time":"2022-05-20T06:46:55.705Z","version":1},{"environment":"blt92be63b2b247a1c5","locale":"en-us","time":"2022-05-20T06:46:55.714Z","version":1},{"environment":"bltef79978048f9cf2a","locale":"en-us","time":"2022-05-20T06:46:55.721Z","version":1}]},"bltdbcb7098b6d20a48":{"uid":"bltdbcb7098b6d20a48","content_type":"image/svg+xml","file_size":"49454","tags":[],"filename":"help-for-the-next-step.svg","url":"https://images.contentstack.io/v3/assets/<api_key>/<asset_uid>/<entity_uid>/<asset_name>","ACL":{"roles":[],"others":{"read":false,"create":false,"update":false,"delete":false,"sub_acl":{"read":false,"create":false,"update":false,"delete":false,"publish":false}}},"is_dir":false,"parent_uid":"blt2f83c9424aeedf29","_version":1,"title":"help-for-the-next-step.svg","publish_details":[{"environment":"blt6f0478243197ef17","locale":"en-us","time":"2022-05-20T06:46:54.550Z","version":1},{"environment":"blt92be63b2b247a1c5","locale":"en-us","time":"2022-05-20T06:46:54.556Z","version":1},{"environment":"bltef79978048f9cf2a","locale":"en-us","time":"2022-05-20T06:46:54.559Z","version":1}]},"blte7d2c0603bd101d9":{"uid":"blte7d2c0603bd101d9","content_type":"image/svg+xml","file_size":"53205","tags":[],"filename":"headless-cms-solution.svg","url":"https://images.contentstack.io/v3/assets/<api_key>/<asset_uid>/<entity_uid>/<asset_name>","ACL":{"roles":[],"others":{"read":false,"create":false,"update":false,"delete":false,"sub_acl":{"read":false,"create":false,"update":false,"delete":false,"publish":false}}},"is_dir":false,"parent_uid":"blt8ea21a022f87ea56","_version":1,"title":"Headless CMS Solution","description":"","publish_details":[{"environment":"blt6f0478243197ef17","locale":"en-us","time":"2022-05-20T06:46:55.995Z","version":1},{"environment":"blt92be63b2b247a1c5","locale":"en-us","time":"2022-05-20T06:46:56.007Z","version":1},{"environment":"bltef79978048f9cf2a","locale":"en-us","time":"2022-05-20T06:46:56.013Z","version":1}]},"bltd1ee323be659616c":{"uid":"bltd1ee323be659616c","content_type":"image/jpeg","file_size":"2850","tags":[],"filename":"ben.jpeg","url":"https://images.contentstack.io/v3/assets/<api_key>/<asset_uid>/<entity_uid>/<asset_name>","ACL":{"roles":[],"others":{"read":false,"create":false,"update":false,"delete":false,"sub_acl":{"read":false,"create":false,"update":false,"delete":false,"publish":false}}},"is_dir":false,"parent_uid":"blt0aebf788c355c655","_version":1,"title":"ben.jpeg","publish_details":[{"environment":"blt6f0478243197ef17","locale":"en-us","time":"2022-05-20T06:46:57.351Z","version":1},{"environment":"blt92be63b2b247a1c5","locale":"en-us","time":"2022-05-20T06:46:57.359Z","version":1},{"environment":"bltef79978048f9cf2a","locale":"en-us","time":"2022-05-20T06:46:57.367Z","version":1}]},"blt88f9721e743a5bae":{"uid":"blt88f9721e743a5bae","content_type":"image/svg+xml","file_size":"706","tags":[],"filename":"bucket1.svg","url":"https://images.contentstack.io/v3/assets/<api_key>/<asset_uid>/<entity_uid>/<asset_name>","ACL":{"roles":[],"others":{"read":false,"create":false,"update":false,"delete":false,"sub_acl":{"read":false,"create":false,"update":false,"delete":false,"publish":false}}},"is_dir":false,"parent_uid":"bltc227ac394f06235b","_version":1,"title":"bucket1.svg","publish_details":[{"environment":"blt6f0478243197ef17","locale":"en-us","time":"2022-05-20T06:46:57.358Z","version":1},{"environment":"blt92be63b2b247a1c5","locale":"en-us","time":"2022-05-20T06:46:57.362Z","version":1},{"environment":"bltef79978048f9cf2a","locale":"en-us","time":"2022-05-20T06:46:57.364Z","version":1}]},"blt2fc7121b15174c44":{"uid":"blt2fc7121b15174c44","content_type":"image/svg+xml","file_size":"706","tags":[],"filename":"artificial-intelligence.svg","url":"https://images.contentstack.io/v3/assets/<api_key>/<asset_uid>/<entity_uid>/<asset_name>","ACL":{"roles":[],"others":{"read":false,"create":false,"update":false,"delete":false,"sub_acl":{"read":false,"create":false,"update":false,"delete":false,"publish":false}}},"is_dir":false,"parent_uid":"blt2f83c9424aeedf29","_version":1,"title":"Artificial Intelligence.svg","description":"","publish_details":[{"environment":"blt6f0478243197ef17","locale":"en-us","time":"2022-05-20T06:46:44.931Z","version":1},{"environment":"blt92be63b2b247a1c5","locale":"en-us","time":"2022-05-20T06:46:44.946Z","version":1},{"environment":"bltef79978048f9cf2a","locale":"en-us","time":"2022-05-20T06:46:44.952Z","version":1}]},"blt1399bbdbd56f6d72":{"uid":"blt1399bbdbd56f6d72","content_type":"image/svg+xml","file_size":"1314","tags":[],"filename":"cloud-computing.svg","url":"https://images.contentstack.io/v3/assets/<api_key>/<asset_uid>/<entity_uid>/<asset_name>","ACL":{"roles":[],"others":{"read":false,"create":false,"update":false,"delete":false,"sub_acl":{"read":false,"create":false,"update":false,"delete":false,"publish":false}}},"is_dir":false,"parent_uid":"blt2f83c9424aeedf29","_version":1,"title":"Cloud Computing","description":"","publish_details":[{"environment":"blt6f0478243197ef17","locale":"en-us","time":"2022-05-20T06:46:44.954Z","version":1},{"environment":"blt92be63b2b247a1c5","locale":"en-us","time":"2022-05-20T06:46:44.960Z","version":1},{"environment":"bltef79978048f9cf2a","locale":"en-us","time":"2022-05-20T06:46:44.966Z","version":1}]},"bltbb6c5f8e14a63ed3":{"uid":"bltbb6c5f8e14a63ed3","content_type":"image/svg+xml","file_size":"1288","tags":[],"filename":"facebook.svg","url":"https://images.contentstack.io/v3/assets/<api_key>/<asset_uid>/<entity_uid>/<asset_name>","ACL":{"roles":[],"others":{"read":false,"create":false,"update":false,"delete":false,"sub_acl":{"read":false,"create":false,"update":false,"delete":false,"publish":false}}},"is_dir":false,"parent_uid":"bltc227ac394f06235b","_version":1,"title":"facebook.svg","publish_details":[{"environment":"blt6f0478243197ef17","locale":"en-us","time":"2022-05-20T06:46:46.182Z","version":1},{"environment":"blt92be63b2b247a1c5","locale":"en-us","time":"2022-05-20T06:46:46.187Z","version":1},{"environment":"bltef79978048f9cf2a","locale":"en-us","time":"2022-05-20T06:46:46.190Z","version":1}]},"blt7f1b8da5839bb4b8":{"uid":"blt7f1b8da5839bb4b8","content_type":"image/svg+xml","file_size":"32495","tags":[],"filename":"traditional-decoupled-_headless-cms.svg","url":"https://images.contentstack.io/v3/assets/<api_key>/<asset_uid>/<entity_uid>/<asset_name>","ACL":{"roles":[],"others":{"read":false,"create":false,"update":false,"delete":false,"sub_acl":{"read":false,"create":false,"update":false,"delete":false,"publish":false}}},"is_dir":false,"parent_uid":"blt8ea21a022f87ea56","_version":1,"title":"Traditional Decoupled Headless CMS","description":"","publish_details":[{"environment":"blt6f0478243197ef17","locale":"en-us","time":"2022-05-20T06:46:48.458Z","version":1},{"environment":"blt92be63b2b247a1c5","locale":"en-us","time":"2022-05-20T06:46:48.464Z","version":1},{"environment":"bltef79978048f9cf2a","locale":"en-us","time":"2022-05-20T06:46:48.470Z","version":1}]},"bltcf54339bb59c7f0a":{"uid":"bltcf54339bb59c7f0a","content_type":"image/jpeg","file_size":"8494","tags":[],"filename":"AlbertEinstein.jpeg","url":"https://images.contentstack.io/v3/assets/<api_key>/<asset_uid>/<entity_uid>/<asset_name>","ACL":{"roles":[],"others":{"read":false,"create":false,"update":false,"delete":false,"sub_acl":{"read":false,"create":false,"update":false,"delete":false,"publish":false}}},"is_dir":false,"parent_uid":"blt0aebf788c355c655","_version":1,"title":"AlbertEinstein.jpeg","publish_details":[{"environment":"blt6f0478243197ef17","locale":"en-us","time":"2022-05-20T06:46:47.351Z","version":1},{"environment":"blt92be63b2b247a1c5","locale":"en-us","time":"2022-05-20T06:46:47.355Z","version":1},{"environment":"bltef79978048f9cf2a","locale":"en-us","time":"2022-05-20T06:46:47.359Z","version":1}]},"blte701ff8c92856e25":{"uid":"blte701ff8c92856e25","content_type":"image/svg+xml","file_size":"579","tags":[],"filename":"Icon_Artwork_1.svg","url":"https://images.contentstack.io/v3/assets/<api_key>/<asset_uid>/<entity_uid>/<asset_name>","ACL":{"roles":[],"others":{"read":false,"create":false,"update":false,"delete":false,"sub_acl":{"read":false,"create":false,"update":false,"delete":false,"publish":false}}},"is_dir":false,"parent_uid":"blt43987a02bf0d77e9","_version":1,"title":"Icon_Artwork_1.svg","publish_details":[{"environment":"blt6f0478243197ef17","locale":"en-us","time":"2022-05-20T06:46:48.874Z","version":1},{"environment":"blt92be63b2b247a1c5","locale":"en-us","time":"2022-05-20T06:46:48.879Z","version":1},{"environment":"bltef79978048f9cf2a","locale":"en-us","time":"2022-05-20T06:46:48.882Z","version":1}]},"blt9e257602d025c1a1":{"uid":"blt9e257602d025c1a1","content_type":"image/svg+xml","file_size":"1314","tags":[],"filename":"bucket2.svg","url":"https://images.contentstack.io/v3/assets/<api_key>/<asset_uid>/<entity_uid>/<asset_name>","ACL":{"roles":[],"others":{"read":false,"create":false,"update":false,"delete":false,"sub_acl":{"read":false,"create":false,"update":false,"delete":false,"publish":false}}},"is_dir":false,"parent_uid":"bltc227ac394f06235b","_version":1,"title":"bucket2.svg","publish_details":[{"environment":"blt6f0478243197ef17","locale":"en-us","time":"2022-05-20T06:46:49.068Z","version":1},{"environment":"blt92be63b2b247a1c5","locale":"en-us","time":"2022-05-20T06:46:49.076Z","version":1},{"environment":"bltef79978048f9cf2a","locale":"en-us","time":"2022-05-20T06:46:49.082Z","version":1}]},"bltfaeed766e445e0ed":{"uid":"bltfaeed766e445e0ed","content_type":"image/svg+xml","file_size":"1849","tags":[],"filename":"Icon_Artwork_2.svg","url":"https://images.contentstack.io/v3/assets/<api_key>/<asset_uid>/<entity_uid>/<asset_name>","ACL":{"roles":[],"others":{"read":false,"create":false,"update":false,"delete":false,"sub_acl":{"read":false,"create":false,"update":false,"delete":false,"publish":false}}},"is_dir":false,"parent_uid":"blt43987a02bf0d77e9","_version":1,"title":"Icon_Artwork_2.svg","publish_details":[{"environment":"blt6f0478243197ef17","locale":"en-us","time":"2022-05-20T06:46:50.074Z","version":1},{"environment":"blt92be63b2b247a1c5","locale":"en-us","time":"2022-05-20T06:46:50.080Z","version":1},{"environment":"bltef79978048f9cf2a","locale":"en-us","time":"2022-05-20T06:46:50.086Z","version":1}]},"blt14221ad8cc06a9e2":{"uid":"blt14221ad8cc06a9e2","content_type":"image/svg+xml","file_size":"1436","tags":[],"filename":"Twitter.svg","url":"https://images.contentstack.io/v3/assets/<api_key>/<asset_uid>/<entity_uid>/<asset_name>","ACL":{"roles":[],"others":{"read":false,"create":false,"update":false,"delete":false,"sub_acl":{"read":false,"create":false,"update":false,"delete":false,"publish":false}}},"is_dir":false,"parent_uid":"bltc227ac394f06235b","_version":1,"title":"Twitter.svg","publish_details":[{"environment":"blt6f0478243197ef17","locale":"en-us","time":"2022-05-20T06:46:49.997Z","version":1},{"environment":"blt92be63b2b247a1c5","locale":"en-us","time":"2022-05-20T06:46:50.004Z","version":1},{"environment":"bltef79978048f9cf2a","locale":"en-us","time":"2022-05-20T06:46:50.011Z","version":1}]},"blt3e43a65f78188198":{"uid":"blt3e43a65f78188198","content_type":"image/svg+xml","file_size":"1053","tags":[],"filename":"security.svg","url":"https://images.contentstack.io/v3/assets/<api_key>/<asset_uid>/<entity_uid>/<asset_name>","ACL":{"roles":[],"others":{"read":false,"create":false,"update":false,"delete":false,"sub_acl":{"read":false,"create":false,"update":false,"delete":false,"publish":false}}},"is_dir":false,"parent_uid":"blt2f83c9424aeedf29","_version":1,"title":"Security","description":"","publish_details":[{"environment":"blt6f0478243197ef17","locale":"en-us","time":"2022-05-20T06:46:51.115Z","version":1},{"environment":"blt92be63b2b247a1c5","locale":"en-us","time":"2022-05-20T06:46:51.123Z","version":1},{"environment":"bltef79978048f9cf2a","locale":"en-us","time":"2022-05-20T06:46:51.131Z","version":1}]},"blt11a634782b6b0afa":{"uid":"blt11a634782b6b0afa","content_type":"image/svg+xml","file_size":"32524","tags":[],"filename":"data-mining.svg","url":"https://images.contentstack.io/v3/assets/<api_key>/<asset_uid>/<entity_uid>/<asset_name>","ACL":{"roles":[],"others":{"read":false,"create":false,"update":false,"delete":false,"sub_acl":{"read":false,"create":false,"update":false,"delete":false,"publish":false}}},"is_dir":false,"parent_uid":"blt8ea21a022f87ea56","_version":1,"title":"Data Mining","description":"","publish_details":[{"environment":"blt6f0478243197ef17","locale":"en-us","time":"2022-05-20T06:46:54.470Z","version":1},{"environment":"blt92be63b2b247a1c5","locale":"en-us","time":"2022-05-20T06:46:54.477Z","version":1},{"environment":"bltef79978048f9cf2a","locale":"en-us","time":"2022-05-20T06:46:54.483Z","version":1}]},"blta99db87af6d5156b":{"uid":"blta99db87af6d5156b","content_type":"image/svg+xml","file_size":"2584878","tags":[],"filename":"map-of-brimingham-city.svg","url":"https://images.contentstack.io/v3/assets/<api_key>/<asset_uid>/<entity_uid>/<asset_name>","ACL":{"roles":[],"others":{"read":false,"create":false,"update":false,"delete":false,"sub_acl":{"read":false,"create":false,"update":false,"delete":false,"publish":false}}},"is_dir":false,"parent_uid":"blt7c5f110eea011a1a","_version":1,"title":"Map Of Birmingham City","description":"","publish_details":[{"environment":"blt6f0478243197ef17","locale":"en-us","time":"2022-05-20T06:46:53.176Z","version":1},{"environment":"blt92be63b2b247a1c5","locale":"en-us","time":"2022-05-20T06:46:53.182Z","version":1},{"environment":"bltef79978048f9cf2a","locale":"en-us","time":"2022-05-20T06:46:53.185Z","version":1}]}}